main.py
mcppix-0.1.13.dist-info/METADATA
mcppix-0.1.13.dist-info/WHEEL
mcppix-0.1.13.dist-info/entry_points.txt
mcppix-0.1.13.dist-info/top_level.txt
mcppix-0.1.13.dist-info/RECORD
