Metadata-Version: 2.4
Name: mcppix
Version: 0.1.13
Summary: xxxxxxAdd your description here
Requires-Python: >=3.12
Requires-Dist: mcp[cli]>=1.6.0
